pywebsocket_rpc/__init__.py
pywebsocket_rpc/client.py
pywebsocket_rpc/common.py
pywebsocket_rpc/server.py
pywebsocket_rpc/websocket_base.py
pywebsocket_rpc/proto/gen/node_pb2.py
tests/conftest.py
tests/test_main.py
tests/test_proto/gen/test_pb2.py
pywebsocket_rpc-0.0.5.dist-info/METADATA
pywebsocket_rpc-0.0.5.dist-info/WHEEL
pywebsocket_rpc-0.0.5.dist-info/top_level.txt
pywebsocket_rpc-0.0.5.dist-info/RECORD
