Metadata-Version: 2.1
Name: pywebsocket-rpc
Version: 0.0.5
Summary: RPC over websockets
Home-page: https://github.com/jafreck/websocket-rpc
Author: jafreck
Author-email: jafreck@microosft.com
License: UNKNOWN
Platform: UNKNOWN
Classifier: Programming Language :: Python :: 3
Classifier: License :: OSI Approved :: MIT License
Classifier: Operating System :: OS Independent
Requires-Python: >=3.6
Requires-Dist: aiohttp
Requires-Dist: aiohttp[speedups]
Requires-Dist: protobuf
Requires-Dist: pyopenssl
Requires-Dist: aiojobs
